src/__init__.py
src/cli.py
src/commands/__init__.py
src/commands/create_dialog/__init__.py
src/commands/create_dialog/script.py
src/commands/create_dialog/templates/base.py
src/commands/create_dialog/templates/with_dto.py
aiogram_dialog_template-0.0.2.dist-info/METADATA
aiogram_dialog_template-0.0.2.dist-info/WHEEL
aiogram_dialog_template-0.0.2.dist-info/entry_points.txt
aiogram_dialog_template-0.0.2.dist-info/RECORD
