Metadata-Version: 2.3
Name: aiogram-dialog-template
Version: 0.0.2
Summary: Cоздание структурированных шаблонов для aiogram-dialog
License: Apache-2.0
Author: Pavel Danilevich
Author-email: danilevitch.pasha@yandex.ru
Requires-Python: >=3.10,<4.0
Classifier: Intended Audience :: Developers
Classifier: License :: OSI Approved :: Apache Software License
Classifier: Operating System :: OS Independent
Classifier: Programming Language :: Python :: 3
Classifier: Programming Language :: Python :: 3.10
Classifier: Programming Language :: Python :: 3.11
Classifier: Programming Language :: Python :: 3.12
Classifier: Programming Language :: Python :: 3.13
Requires-Dist: click (>=8.2.1,<9.0.0)
Requires-Dist: loguru (>=0.7.3,<0.8.0)
Project-URL: bug-tracker, https://github.com/pasha-danilevich/aiogram-dialog-template/issues
Project-URL: homepage, https://github.com/pasha-danilevich/aiogram-dialog-template
